gradio_neouploadbutton/__init__.py
gradio_neouploadbutton/neouploadbutton.py
gradio_neouploadbutton/neouploadbutton.pyi
gradio_neouploadbutton/templates/component/index.js
gradio_neouploadbutton/templates/component/style.css
gradio_neouploadbutton/templates/example/index.js
gradio_neouploadbutton/templates/example/style.css
gradio_neouploadbutton-0.0.9.dist-info/METADATA
gradio_neouploadbutton-0.0.9.dist-info/WHEEL
gradio_neouploadbutton-0.0.9.dist-info/RECORD
